odoo/addons/ssi_psychology_case/README.rst
odoo/addons/ssi_psychology_case/__init__.py
odoo/addons/ssi_psychology_case/__manifest__.py
odoo/addons/ssi_psychology_case/data/approval_template_data.xml
odoo/addons/ssi_psychology_case/data/ir_sequence_data.xml
odoo/addons/ssi_psychology_case/data/policy_template_data.xml
odoo/addons/ssi_psychology_case/data/sequence_template_data.xml
odoo/addons/ssi_psychology_case/demo/account_account_demo.xml
odoo/addons/ssi_psychology_case/demo/account_analytic_group_demo.xml
odoo/addons/ssi_psychology_case/demo/account_journal_demo.xml
odoo/addons/ssi_psychology_case/demo/psychology_case_type_demo.xml
odoo/addons/ssi_psychology_case/models/__init__.py
odoo/addons/ssi_psychology_case/models/psychology_case.py
odoo/addons/ssi_psychology_case/models/psychology_case_tax.py
odoo/addons/ssi_psychology_case/models/psychology_case_type.py
odoo/addons/ssi_psychology_case/models/psychology_service.py
odoo/addons/ssi_psychology_case/models/psychology_service_type.py
odoo/addons/ssi_psychology_case/security/ir.model.access.csv
odoo/addons/ssi_psychology_case/security/ir_module_category_data.xml
odoo/addons/ssi_psychology_case/security/ir_rule_data.xml
odoo/addons/ssi_psychology_case/security/res_group_data.xml
odoo/addons/ssi_psychology_case/static/description/icon.png
odoo/addons/ssi_psychology_case/views/psychology_case_type_views.xml
odoo/addons/ssi_psychology_case/views/psychology_case_views.xml
odoo14_addon_ssi_psychology_case-14.0.1.4.0.dist-info/METADATA
odoo14_addon_ssi_psychology_case-14.0.1.4.0.dist-info/WHEEL
odoo14_addon_ssi_psychology_case-14.0.1.4.0.dist-info/top_level.txt
odoo14_addon_ssi_psychology_case-14.0.1.4.0.dist-info/RECORD
